Metadata-Version: 2.1
Name: xdc
Version: 1.0.1
Summary: xdc.py is a Python library for interacting with XDC (XinFin Digital Contract) tokens using web3.py
Home-page: https://github.com/Ziusz/xdc.py
Author: Ziusz
Author-email: ziusz@outlook.com
License: MIT
Keywords: xdc sdk web3.py smartcontract token xrc20 xrc721 xinfin digital contract web3
Classifier: Development Status :: 4 - Beta
Classifier: Intended Audience :: Developers
Classifier: License :: OSI Approved :: MIT License
Classifier: Programming Language :: Python :: 3
Classifier: Operating System :: OS Independent
Classifier: Programming Language :: Python :: 3
Classifier: Programming Language :: Python :: 3.8
Classifier: Programming Language :: Python :: 3.9
Classifier: Programming Language :: Python :: 3.10
Classifier: Programming Language :: Python :: 3.11
Classifier: Programming Language :: Python :: 3.12
Requires-Python: >=3.8, <4
License-File: LICENSE
Requires-Dist: web3>=6.18.0
